sqlalchemy_pydantic_crud/__init__.py
sqlalchemy_pydantic_crud/crud/__init__.py
sqlalchemy_pydantic_crud/crud/base.py
sqlalchemy_pydantic_crud/crud/decorators.py
sqlalchemy_pydantic_crud/crud/helpers.py
sqlalchemy_pydantic_crud/exceptions/__init__.py
sqlalchemy_pydantic_crud/exceptions/crud.py
sqlalchemy_pydantic_crud/interface/__init__.py
sqlalchemy_pydantic_crud/interface/crud.py
sqlalchemy_pydantic_crud/interface/session.py
sqlalchemy_pydantic_crud/models/__init__.py
sqlalchemy_pydantic_crud/models/model.py
sqlalchemy_pydantic_crud/models/schema.py
sqlalchemy_pydantic_crud-0.1.16.dist-info/LICENSE
sqlalchemy_pydantic_crud-0.1.16.dist-info/METADATA
sqlalchemy_pydantic_crud-0.1.16.dist-info/WHEEL
sqlalchemy_pydantic_crud-0.1.16.dist-info/top_level.txt
sqlalchemy_pydantic_crud-0.1.16.dist-info/RECORD
