Metadata-Version: 2.1
Name: sqlalchemy_pydantic_crud
Version: 0.1.16
Summary: Base CRUD for SqlAlchemy
Home-page: https://github.com/yourusername/your_package_name
Author: Denisov Pavel
Author-email: denisov.p.g@gmail.com
Classifier: Programming Language :: Python :: 3
Classifier: License :: OSI Approved :: MIT License
Classifier: Operating System :: OS Independent
Requires-Python: >=3.10
License-File: LICENSE
